apa_logbook_parser/__init__.py
apa_logbook_parser/project_uuid.py
apa_logbook_parser/airports_db/__init__.py
apa_logbook_parser/airports_db/airport.py
apa_logbook_parser/airports_db/airports.py
apa_logbook_parser/apa_2023_02/__init__.py
apa_logbook_parser/apa_2023_02/models/__init__.py
apa_logbook_parser/apa_2023_02/models/expanded.py
apa_logbook_parser/apa_2023_02/models/expanded_flat.py
apa_logbook_parser/apa_2023_02/models/metadata.py
apa_logbook_parser/apa_2023_02/models/pydantic_json_mixin.py
apa_logbook_parser/apa_2023_02/models/raw.py
apa_logbook_parser/apa_2023_02/models/raw_flat.py
apa_logbook_parser/apa_2023_02/parser/__init__.py
apa_logbook_parser/apa_2023_02/parser/expand_raw.py
apa_logbook_parser/apa_2023_02/parser/flatten_expanded.py
apa_logbook_parser/apa_2023_02/parser/flatten_raw.py
apa_logbook_parser/apa_2023_02/parser/parse_context.py
apa_logbook_parser/apa_2023_02/parser/parse_xml_logbook.py
apa_logbook_parser/apa_2023_02/parser/transform.py
apa_logbook_parser/apa_2023_02/validation/__init__.py
apa_logbook_parser/cli/__init__.py
apa_logbook_parser/cli/diff.py
apa_logbook_parser/cli/main.py
apa_logbook_parser/cli/parse.py
apa_logbook_parser/cli/translate.py
apa_logbook_parser/snippets/__init__.py
apa_logbook_parser/snippets/click/__init__.py
apa_logbook_parser/snippets/click/check_file_output_path.py
apa_logbook_parser/snippets/click/task_complete.py
apa_logbook_parser/snippets/datetime/__init__.py
apa_logbook_parser/snippets/datetime/complete_partial_datetime.py
apa_logbook_parser/snippets/datetime/datetime_from_struct_time.py
apa_logbook_parser/snippets/datetime/factored_duration.py
apa_logbook_parser/snippets/datetime/parse_duration_regex.py
apa_logbook_parser/snippets/file/__init__.py
apa_logbook_parser/snippets/file/clean_filename.py
apa_logbook_parser/snippets/file/dicts_to_csv.py
apa_logbook_parser/snippets/file/json_mixin.py
apa_logbook_parser/snippets/file/remove_blank_lines.py
apa_logbook_parser/snippets/file/validate_file_out.py
apa_logbook_parser-0.1.1.dist-info/entry_points.txt
apa_logbook_parser-0.1.1.dist-info/LICENSE
apa_logbook_parser-0.1.1.dist-info/WHEEL
apa_logbook_parser-0.1.1.dist-info/METADATA
apa_logbook_parser-0.1.1.dist-info/RECORD
